{
  "packageId": "com.dkayode.nook",
  "host": "nook.k4yod3.com",
  "name": "Nook",
  "launcherName": "Nook",
  "display": "standalone",
  "themeColor": "#0b0b0f",
  "navigationColor": "#0b0b0f",
  "navigationColorDark": "#0b0b0f",
  "navigationDividerColor": "#0b0b0f",
  "navigationDividerColorDark": "#0b0b0f",
  "backgroundColor": "#0b0b0f",
  "enableNotifications": false,
  "startUrl": "/dashboard",
  "iconUrl": "https://nook.k4yod3.com/icons/icon-512.png",
  "maskableIconUrl": "https://nook.k4yod3.com/icons/icon-maskable-512.png",
  "shortcuts": [],
  "generatorApp": "bubblewrap-cli",
  "orientation": "portrait",
  "fingerprints": [],
  "fallbackType": "customtabs",
  "features": {},
  "alphaDependencies": { "enabled": false },
  "enableSiteSettingsShortcut": true,
  "isChromeOSOnly": false,
  "isMetaQuest": false,
  "fullScopeUrl": "https://nook.k4yod3.com/"
}
